{
  "companies": [
    {
      "id": "COMP-001",
      "name": "Equity Bank",
      "category": "Banking & Financial Services",
      "subcategory": "Commercial Banks",
      "tier": "premium",
      "logo": "https://upload.wikimedia.org/wikipedia/commons/thumb/8/8a/Equity_Bank_Kenya_logo.svg/1200px-Equity_Bank_Kenya_logo.svg.png",
      "website": "https://equitybank.co.ke",
      "auctionEligible": true,
      "maxBidAmount": 1000000,
      "description": "Leading commercial bank with largest customer base in Kenya",
      "industry": "Banking",
      "founded": 1984,
      "headquarters": "Nairobi, Kenya"
    },
    {
      "id": "COMP-002",
      "name": "Safaricom",
      "category": "Telecommunications & ICT",
      "subcategory": "Mobile Operators",
      "tier": "premium",
      "logo": "https://upload.wikimedia.org/wikipedia/commons/thumb/8/8a/Safaricom_logo.svg/1200px-Safaricom_logo.svg.png",
      "website": "https://safaricom.co.ke",
      "auctionEligible": true,
      "maxBidAmount": 2000000,
      "description": "Kenya's largest mobile operator and M-Pesa pioneer",
      "industry": "Telecommunications",
      "founded": 1997,
      "headquarters": "Nairobi, Kenya"
    },
    {
      "id": "COMP-003",
      "name": "KCB Group",
      "category": "Banking & Financial Services",
      "subcategory": "Commercial Banks",
      "tier": "premium",
      "logo": "https://upload.wikimedia.org/wikipedia/commons/thumb/8/8a/KCB_Group_logo.svg/1200px-KCB_Group_logo.svg.png",
      "website": "https://kcbgroup.com",
      "auctionEligible": true,
      "maxBidAmount": 1500000,
      "description": "Largest bank by assets in East Africa",
      "industry": "Banking",
      "founded": 1896,
      "headquarters": "Nairobi, Kenya"
    },
    {
      "id": "COMP-004",
      "name": "Cooperative Bank",
      "category": "Banking & Financial Services",
      "subcategory": "Commercial Banks",
      "tier": "premium",
      "logo": "https://www.co-opbank.co.ke/wp-content/uploads/2020/03/co-op-bank-logo.png",
      "website": "https://co-opbank.co.ke",
      "auctionEligible": true,
      "maxBidAmount": 800000,
      "description": "Major cooperative bank serving over 9 million customers",
      "industry": "Banking",
      "founded": 1965,
      "headquarters": "Nairobi, Kenya"
    },
    {
      "id": "COMP-005",
      "name": "ABSA Kenya",
      "category": "Banking & Financial Services",
      "subcategory": "Commercial Banks",
      "tier": "premium",
      "logo": "https://www.absa.co.ke/wp-content/uploads/2020/03/absa-logo.png",
      "website": "https://absa.co.ke",
      "auctionEligible": true,
      "maxBidAmount": 1200000,
      "description": "International bank with strong Kenyan presence",
      "industry": "Banking",
      "founded": 1904,
      "headquarters": "Nairobi, Kenya"
    },
    {
      "id": "COMP-006",
      "name": "Airtel Kenya",
      "category": "Telecommunications & ICT",
      "subcategory": "Mobile Operators",
      "tier": "premium",
      "logo": "https://www.airtel.co.ke/wp-content/uploads/2020/03/airtel-logo.png",
      "website": "https://airtel.co.ke",
      "auctionEligible": true,
      "maxBidAmount": 1000000,
      "description": "Second largest mobile operator in Kenya",
      "industry": "Telecommunications",
      "founded": 2000,
      "headquarters": "Nairobi, Kenya"
    },
    {
      "id": "COMP-007",
      "name": "Telkom Kenya",
      "category": "Telecommunications & ICT",
      "subcategory": "Mobile Operators",
      "tier": "standard",
      "logo": "https://www.telkom.co.ke/wp-content/uploads/2020/03/telkom-logo.png",
      "website": "https://telkom.co.ke",
      "auctionEligible": true,
      "maxBidAmount": 600000,
      "description": "Fixed line and mobile telecommunications provider",
      "industry": "Telecommunications",
      "founded": 1999,
      "headquarters": "Nairobi, Kenya"
    },
    {
      "id": "COMP-008",
      "name": "Zuku",
      "category": "Telecommunications & ICT",
      "subcategory": "ISPs",
      "tier": "standard",
      "logo": "https://www.zuku.co.ke/wp-content/uploads/2020/03/zuku-logo.png",
      "website": "https://zuku.co.ke",
      "auctionEligible": true,
      "maxBidAmount": 400000,
      "description": "Leading internet service provider in Kenya",
      "industry": "Internet Service",
      "founded": 2009,
      "headquarters": "Nairobi, Kenya"
    },
    {
      "id": "COMP-009",
      "name": "Naivas",
      "category": "Retail & Wholesale Trade",
      "subcategory": "Supermarket Chains",
      "tier": "premium",
      "logo": "https://www.naivas.co.ke/wp-content/uploads/2020/03/naivas-logo.png",
      "website": "https://naivas.co.ke",
      "auctionEligible": true,
      "maxBidAmount": 800000,
      "description": "Largest supermarket chain in Kenya",
      "industry": "Retail",
      "founded": 1990,
      "headquarters": "Nairobi, Kenya"
    },
    {
      "id": "COMP-010",
      "name": "Jumia Kenya",
      "category": "E-commerce & Digital Trade",
      "subcategory": "Online Marketplaces",
      "tier": "premium",
      "logo": "https://www.jumia.co.ke/wp-content/uploads/2020/03/jumia-logo.png",
      "website": "https://jumia.co.ke",
      "auctionEligible": true,
      "maxBidAmount": 1000000,
      "description": "Leading e-commerce platform in Kenya",
      "industry": "E-commerce",
      "founded": 2012,
      "headquarters": "Nairobi, Kenya"
    },
    {
      "id": "COMP-011",
      "name": "Carrefour",
      "category": "Retail & Wholesale Trade",
      "subcategory": "Supermarket Chains",
      "tier": "premium",
      "logo": "https://www.carrefour.co.ke/wp-content/uploads/2020/03/carrefour-logo.png",
      "website": "https://carrefour.co.ke",
      "auctionEligible": true,
      "maxBidAmount": 1200000,
      "description": "International retail giant with Kenyan presence",
      "industry": "Retail",
      "founded": 1958,
      "headquarters": "Nairobi, Kenya"
    },
    {
      "id": "COMP-012",
      "name": "Quickmart",
      "category": "Retail & Wholesale Trade",
      "subcategory": "Supermarket Chains",
      "tier": "standard",
      "logo": "https://www.quickmart.co.ke/wp-content/uploads/2020/03/quickmart-logo.png",
      "website": "https://quickmart.co.ke",
      "auctionEligible": true,
      "maxBidAmount": 500000,
      "description": "Growing supermarket chain with modern retail approach",
      "industry": "Retail",
      "founded": 2006,
      "headquarters": "Nairobi, Kenya"
    },
    {
      "id": "COMP-013",
      "name": "Bidco Africa",
      "category": "Manufacturing & Processing",
      "subcategory": "Food & Beverages",
      "tier": "premium",
      "logo": "https://www.bidcoafrica.com/wp-content/uploads/2020/03/bidco-logo.png",
      "website": "https://bidcoafrica.com",
      "auctionEligible": true,
      "maxBidAmount": 1500000,
      "description": "Largest FMCG manufacturer in East Africa",
      "industry": "Manufacturing",
      "founded": 1970,
      "headquarters": "Thika, Kenya"
    },
    {
      "id": "COMP-014",
      "name": "Brookside Dairy",
      "category": "Manufacturing & Processing",
      "subcategory": "Food & Beverages",
      "tier": "premium",
      "logo": "https://www.brookside.co.ke/wp-content/uploads/2020/03/brookside-logo.png",
      "website": "https://brookside.co.ke",
      "auctionEligible": true,
      "maxBidAmount": 1000000,
      "description": "Leading dairy company with extensive product range",
      "industry": "Manufacturing",
      "founded": 1993,
      "headquarters": "Nairobi, Kenya"
    },
    {
      "id": "COMP-015",
      "name": "Unga Group",
      "category": "Manufacturing & Processing",
      "subcategory": "Food & Beverages",
      "tier": "standard",
      "logo": "https://www.ungakenya.com/wp-content/uploads/2020/03/unga-logo.png",
      "website": "https://ungakenya.com",
      "auctionEligible": true,
      "maxBidAmount": 600000,
      "description": "Major food processor and miller",
      "industry": "Manufacturing",
      "founded": 1908,
      "headquarters": "Nairobi, Kenya"
    },
    {
      "id": "COMP-016",
      "name": "East African Breweries",
      "category": "Manufacturing & Processing",
      "subcategory": "Food & Beverages",
      "tier": "premium",
      "logo": "https://www.eabl.com/wp-content/uploads/2020/03/eabl-logo.png",
      "website": "https://eabl.com",
      "auctionEligible": true,
      "maxBidAmount": 1800000,
      "description": "Leading beverage manufacturer and distributor",
      "industry": "Manufacturing",
      "founded": 1922,
      "headquarters": "Nairobi, Kenya"
    },
    {
      "id": "COMP-017",
      "name": "Kenya Power",
      "category": "Energy & Utilities",
      "subcategory": "Power Generation",
      "tier": "premium",
      "logo": "https://www.kplc.co.ke/wp-content/uploads/2020/03/kenya-power-logo.png",
      "website": "https://kplc.co.ke",
      "auctionEligible": true,
      "maxBidAmount": 1200000,
      "description": "National electricity distributor and utility company",
      "industry": "Energy",
      "founded": 1997,
      "headquarters": "Nairobi, Kenya"
    },
    {
      "id": "COMP-018",
      "name": "KenGen",
      "category": "Energy & Utilities",
      "subcategory": "Power Generation",
      "tier": "premium",
      "logo": "https://www.kengen.co.ke/wp-content/uploads/2020/03/kengen-logo.png",
      "website": "https://kengen.co.ke",
      "auctionEligible": true,
      "maxBidAmount": 1000000,
      "description": "Leading power generation company in Kenya",
      "industry": "Energy",
      "founded": 1954,
      "headquarters": "Nairobi, Kenya"
    },
    {
      "id": "COMP-019",
      "name": "TotalEnergies Kenya",
      "category": "Energy & Utilities",
      "subcategory": "Oil & Gas",
      "tier": "premium",
      "logo": "https://www.totalenergies.co.ke/wp-content/uploads/2020/03/total-logo.png",
      "website": "https://totalenergies.co.ke",
      "auctionEligible": true,
      "maxBidAmount": 1500000,
      "description": "Major oil and gas company with extensive network",
      "industry": "Energy",
      "founded": 1924,
      "headquarters": "Nairobi, Kenya"
    },
    {
      "id": "COMP-020",
      "name": "Rubis Energy",
      "category": "Energy & Utilities",
      "subcategory": "Oil & Gas",
      "tier": "standard",
      "logo": "https://www.rubis-kenya.com/wp-content/uploads/2020/03/rubis-logo.png",
      "website": "https://rubis-kenya.com",
      "auctionEligible": true,
      "maxBidAmount": 800000,
      "description": "Fuel distribution and retail company",
      "industry": "Energy",
      "founded": 1990,
      "headquarters": "Nairobi, Kenya"
    },
    {
      "id": "COMP-021",
      "name": "M-Kopa",
      "category": "Energy & Utilities",
      "subcategory": "Renewable Energy",
      "tier": "standard",
      "logo": "https://www.m-kopa.com/wp-content/uploads/2020/03/mkopa-logo.png",
      "website": "https://m-kopa.com",
      "auctionEligible": true,
      "maxBidAmount": 400000,
      "description": "Solar energy and fintech company",
      "industry": "Energy",
      "founded": 2011,
      "headquarters": "Nairobi, Kenya"
    },
    {
      "id": "COMP-022",
      "name": "Twiga Foods",
      "category": "E-commerce & Digital Trade",
      "subcategory": "B2B Platforms",
      "tier": "standard",
      "logo": "https://www.twiga.com/wp-content/uploads/2020/03/twiga-logo.png",
      "website": "https://twiga.com",
      "auctionEligible": true,
      "maxBidAmount": 300000,
      "description": "Food distribution and B2B platform",
      "industry": "E-commerce",
      "founded": 2014,
      "headquarters": "Nairobi, Kenya"
    },
    {
      "id": "COMP-023",
      "name": "Sendy",
      "category": "E-commerce & Digital Trade",
      "subcategory": "Delivery Apps",
      "tier": "standard",
      "logo": "https://www.sendy.co/wp-content/uploads/2020/03/sendy-logo.png",
      "website": "https://sendy.co",
      "auctionEligible": true,
      "maxBidAmount": 250000,
      "description": "Logistics and delivery platform",
      "industry": "Logistics",
      "founded": 2015,
      "headquarters": "Nairobi, Kenya"
    },
    {
      "id": "COMP-024",
      "name": "Glovo",
      "category": "E-commerce & Digital Trade",
      "subcategory": "Delivery Apps",
      "tier": "standard",
      "logo": "https://www.glovoapp.com/wp-content/uploads/2020/03/glovo-logo.png",
      "website": "https://glovoapp.com",
      "auctionEligible": true,
      "maxBidAmount": 300000,
      "description": "International food delivery platform",
      "industry": "Delivery",
      "founded": 2015,
      "headquarters": "Nairobi, Kenya"
    },
    {
      "id": "COMP-025",
      "name": "Uber Eats",
      "category": "E-commerce & Digital Trade",
      "subcategory": "Delivery Apps",
      "tier": "premium",
      "logo": "https://www.ubereats.com/wp-content/uploads/2020/03/uber-eats-logo.png",
      "website": "https://ubereats.com",
      "auctionEligible": true,
      "maxBidAmount": 800000,
      "description": "Global food delivery service",
      "industry": "Delivery",
      "founded": 2014,
      "headquarters": "Nairobi, Kenya"
    },
    {
      "id": "COMP-026",
      "name": "Bamburi Cement",
      "category": "Manufacturing & Processing",
      "subcategory": "Cement & Construction",
      "tier": "premium",
      "logo": "https://www.bamburi-cement.co.ke/wp-content/uploads/2020/03/bamburi-logo.png",
      "website": "https://bamburi-cement.co.ke",
      "auctionEligible": true,
      "maxBidAmount": 1000000,
      "description": "Leading cement manufacturer in East Africa",
      "industry": "Manufacturing",
      "founded": 1951,
      "headquarters": "Mombasa, Kenya"
    },
    {
      "id": "COMP-027",
      "name": "Devki Steel",
      "category": "Manufacturing & Processing",
      "subcategory": "Cement & Construction",
      "tier": "standard",
      "logo": "https://www.devkisteel.com/wp-content/uploads/2020/03/devki-logo.png",
      "website": "https://devkisteel.com",
      "auctionEligible": true,
      "maxBidAmount": 500000,
      "description": "Steel manufacturing and construction materials",
      "industry": "Manufacturing",
      "founded": 1987,
      "headquarters": "Nairobi, Kenya"
    },
    {
      "id": "COMP-028",
      "name": "Isuzu East Africa",
      "category": "Manufacturing & Processing",
      "subcategory": "Automotive Assembly",
      "tier": "premium",
      "logo": "https://www.isuzu.co.ke/wp-content/uploads/2020/03/isuzu-logo.png",
      "website": "https://isuzu.co.ke",
      "auctionEligible": true,
      "maxBidAmount": 1200000,
      "description": "Automotive assembly and distribution",
      "industry": "Automotive",
      "founded": 1977,
      "headquarters": "Nairobi, Kenya"
    },
    {
      "id": "COMP-029",
      "name": "Toyota Kenya",
      "category": "Manufacturing & Processing",
      "subcategory": "Automotive Assembly",
      "tier": "premium",
      "logo": "https://www.toyota.co.ke/wp-content/uploads/2020/03/toyota-logo.png",
      "website": "https://toyota.co.ke",
      "auctionEligible": true,
      "maxBidAmount": 1500000,
      "description": "Leading automotive distributor in Kenya",
      "industry": "Automotive",
      "founded": 1977,
      "headquarters": "Nairobi, Kenya"
    },
    {
      "id": "COMP-030",
      "name": "KTDA",
      "category": "Agriculture & Agribusiness",
      "subcategory": "Tea, Coffee & Horticulture",
      "tier": "premium",
      "logo": "https://www.ktdateas.com/wp-content/uploads/2020/03/ktda-logo.png",
      "website": "https://ktdateas.com",
      "auctionEligible": true,
      "maxBidAmount": 800000,
      "description": "Kenya Tea Development Agency",
      "industry": "Agriculture",
      "founded": 1964,
      "headquarters": "Nairobi, Kenya"
    },
    {
      "id": "COMP-031",
      "name": "Finlays",
      "category": "Agriculture & Agribusiness",
      "subcategory": "Tea, Coffee & Horticulture",
      "tier": "standard",
      "logo": "https://www.finlays.com/wp-content/uploads/2020/03/finlays-logo.png",
      "website": "https://finlays.com",
      "auctionEligible": true,
      "maxBidAmount": 600000,
      "description": "Agricultural products and tea processing",
      "industry": "Agriculture",
      "founded": 1750,
      "headquarters": "Kericho, Kenya"
    },
    {
      "id": "COMP-032",
      "name": "New KCC",
      "category": "Agriculture & Agribusiness",
      "subcategory": "Dairy & Livestock",
      "tier": "standard",
      "logo": "https://www.newkcc.co.ke/wp-content/uploads/2020/03/newkcc-logo.png",
      "website": "https://newkcc.co.ke",
      "auctionEligible": true,
      "maxBidAmount": 400000,
      "description": "New Kenya Cooperative Creameries",
      "industry": "Agriculture",
      "founded": 1925,
      "headquarters": "Nairobi, Kenya"
    },
    {
      "id": "COMP-033",
      "name": "Del Monte Kenya",
      "category": "Agriculture & Agribusiness",
      "subcategory": "Large Farms & Exports",
      "tier": "premium",
      "logo": "https://www.delmonte.co.ke/wp-content/uploads/2020/03/delmonte-logo.png",
      "website": "https://delmonte.co.ke",
      "auctionEligible": true,
      "maxBidAmount": 800000,
      "description": "Large-scale fruit farming and export",
      "industry": "Agriculture",
      "founded": 1972,
      "headquarters": "Thika, Kenya"
    },
    {
      "id": "COMP-034",
      "name": "Centum Real Estate",
      "category": "Construction & Real Estate",
      "subcategory": "Developers",
      "tier": "premium",
      "logo": "https://www.centum.co.ke/wp-content/uploads/2020/03/centum-logo.png",
      "website": "https://centum.co.ke",
      "auctionEligible": true,
      "maxBidAmount": 1200000,
      "description": "Leading real estate development company",
      "industry": "Real Estate",
      "founded": 1967,
      "headquarters": "Nairobi, Kenya"
    },
    {
      "id": "COMP-035",
      "name": "Mi Vida",
      "category": "Construction & Real Estate",
      "subcategory": "Developers",
      "tier": "standard",
      "logo": "https://www.mivida.co.ke/wp-content/uploads/2020/03/mivida-logo.png",
      "website": "https://mivida.co.ke",
      "auctionEligible": true,
      "maxBidAmount": 600000,
      "description": "Affordable housing development company",
      "industry": "Real Estate",
      "founded": 2015,
      "headquarters": "Nairobi, Kenya"
    }
  ],
  "metadata": {
    "totalCompanies": 35,
    "categories": 5,
    "premiumTier": 20,
    "standardTier": 15,
    "lastUpdated": "2024-01-15T10:00:00Z",
    "version": "1.0.0"
  }
} 